pypi_version_check/__init__.py
pypi_version_check/__main__.py
pypi_version_check-0.0.0.dist-info/COPYING
pypi_version_check-0.0.0.dist-info/METADATA
pypi_version_check-0.0.0.dist-info/WHEEL
pypi_version_check-0.0.0.dist-info/entry_points.txt
pypi_version_check-0.0.0.dist-info/top_level.txt
pypi_version_check-0.0.0.dist-info/RECORD
