Metadata-Version: 2.1
Name: pypi-version-check
Version: 0.0.0
Summary: PyPI Version Check
Home-page: https://gitlab.com/pypi-version-check/pypi-version-check
Author: Simó Albert i Beltran
Author-email: sim6@bona.gent
License: AGPL-3.0-or-later
Project-URL: Bug Reports, https://gitlab.com/pypi-version-check/pypi-version-check/-/issues
Project-URL: Funding, https://liberapay.com/sim6/donate
Project-URL: Source, https://gitlab.com/pypi-version-check/pypi-version-check/-/tree/master
Keywords: pypi
Platform: UNKNOWN
Classifier: Development Status :: 5 - Production/Stable
Classifier: License :: OSI Approved :: GNU Affero General Public License v3 or later (AGPLv3+)
Classifier: Programming Language :: Python
Classifier: Programming Language :: Python :: 3 :: Only
Classifier: Programming Language :: Python :: 3.7
Classifier: Programming Language :: Python :: 3.9
Requires-Python: >=3.7, <4
Requires-Dist: click
Requires-Dist: click-log
Requires-Dist: requests
Provides-Extra: test
Requires-Dist: isort ; extra == 'test'
Requires-Dist: black ; extra == 'test'
Requires-Dist: bandit ; extra == 'test'
Requires-Dist: flake8 ; extra == 'test'
Requires-Dist: pylint ; extra == 'test'
Requires-Dist: mamba ; extra == 'test'
Requires-Dist: expects ; extra == 'test'
Requires-Dist: coverage ; extra == 'test'
